repo2llm/__init__.py
repo2llm/cli.py
repo2llm/config.py
repo2llm/constants.py
repo2llm/core.py
repo2llm/formatters/__init__.py
repo2llm/formatters/base.py
repo2llm/formatters/generic.py
repo2llm/formatters/javascript.py
repo2llm/formatters/json.py
repo2llm/formatters/markdown.py
repo2llm/formatters/python.py
repo2llm/formatters/toml.py
repo2llm/formatters/typescript.py
repo2llm/formatters/yaml.py
repo2llm-1.1.1.dist-info/LICENSE
repo2llm-1.1.1.dist-info/METADATA
repo2llm-1.1.1.dist-info/WHEEL
repo2llm-1.1.1.dist-info/entry_points.txt
repo2llm-1.1.1.dist-info/RECORD
