Metadata-Version: 2.3
Name: repo2llm
Version: 1.1.1
Summary: A tool to easily share repository contents with LLMs through the clipboard.
Author: Forest Dussault
Author-email: forestdussault@gmail.com
Requires-Python: >=3.11,<4.0
Classifier: Programming Language :: Python :: 3
Classifier: Programming Language :: Python :: 3.11
Classifier: Programming Language :: Python :: 3.12
Classifier: Programming Language :: Python :: 3.13
Requires-Dist: click (>=8.1.7,<9.0.0)
Requires-Dist: pydantic (>=2.9.2,<3.0.0)
Requires-Dist: pyperclip (>=1.9.0,<2.0.0)
Requires-Dist: rich (>=13.9.4,<14.0.0)
